package_for_dynamic_pricing_of_airline_ancillaries/MultipleAncillaryProductsNonlinearDemand.py
package_for_dynamic_pricing_of_airline_ancillaries/__init__.py
package_for_dynamic_pricing_of_airline_ancillaries-0.0.1.dist-info/LICENSE
package_for_dynamic_pricing_of_airline_ancillaries-0.0.1.dist-info/METADATA
package_for_dynamic_pricing_of_airline_ancillaries-0.0.1.dist-info/WHEEL
package_for_dynamic_pricing_of_airline_ancillaries-0.0.1.dist-info/top_level.txt
package_for_dynamic_pricing_of_airline_ancillaries-0.0.1.dist-info/RECORD
